rad_embeddings/__init__.py
rad_embeddings/encoder.py
rad_embeddings/model.py
rad_embeddings/storage.zip
rad_embeddings/train_token_env_policy.py
rad_embeddings/storage/DFAEnv-v0-encoder.zip
rad_embeddings/storage/DFAEnv-v1-encoder.zip
rad_embeddings/storage/runs/PPO_1/events.out.tfevents.1736972161.wifi-10-42-144-50.wifi.berkeley.edu.11863.0
rad_embeddings/storage/runs/PPO_2/events.out.tfevents.1736974344.wifi-10-42-144-50.wifi.berkeley.edu.12484.0
rad_embeddings/token_env_reach_avoid_policy/runs/PPO_1/events.out.tfevents.1736976150.wifi-10-42-144-50.wifi.berkeley.edu.13134.0
rad_embeddings/token_env_reach_avoid_policy/runs/PPO_2/events.out.tfevents.1736977165.wifi-10-42-144-50.wifi.berkeley.edu.13539.0
rad_embeddings/token_env_reach_avoid_policy/runs/PPO_3/events.out.tfevents.1736977297.wifi-10-42-144-50.wifi.berkeley.edu.13580.0
rad_embeddings/utils/__init__.py
rad_embeddings/utils/sb3_dfa_env_features_extractor.py
rad_embeddings/utils/sb3_logger_callback.py
rad_embeddings/utils/sb3_token_env_features_extractor.py
rad_embeddings/utils/utils.py
rad_embeddings-0.1.2.dist-info/METADATA
rad_embeddings-0.1.2.dist-info/WHEEL
rad_embeddings-0.1.2.dist-info/licenses/LICENSE
rad_embeddings-0.1.2.dist-info/RECORD
