Metadata-Version: 2.4
Name: rad-embeddings
Version: 0.1.2
Summary: RAD Embeddings
License-File: LICENSE
Requires-Python: >=3.12
Requires-Dist: dfa-gym>=0.1.0
Requires-Dist: stable-baselines3>=2.4.1
Requires-Dist: tensorboard>=2.18.0
Requires-Dist: token-env>=0.2.1
Requires-Dist: torch-geometric>=2.6.1
Requires-Dist: torch<2.3.0
